htranslate/__init__.py
htranslate/translator.py
htranslate-1.0.1.dist-info/WHEEL
htranslate-1.0.1.dist-info/METADATA
htranslate-1.0.1.dist-info/RECORD
